.travis.yml
AUTHORS.rst
CHANGES.rst
LICENSE
MANIFEST.in
README.rst
config.yml
pytest.ini
run-tests.sh
setup.cfg
setup.py
record_recommender/__init__.py
record_recommender/app.py
record_recommender/cli.py
record_recommender/fetcher.py
record_recommender/profiles.py
record_recommender/recommender.py
record_recommender/storage.py
record_recommender/utils.py
record_recommender/version.py
record_recommender.egg-info/PKG-INFO
record_recommender.egg-info/SOURCES.txt
record_recommender.egg-info/dependency_links.txt
record_recommender.egg-info/entry_points.txt
record_recommender.egg-info/not-zip-safe
record_recommender.egg-info/requires.txt
record_recommender.egg-info/top_level.txt
tests/test_app.py