Metadata-Version: 1.1
Name: record-recommender
Version: 0.0.2
Summary: Record to Record Recommendations for Invenio.
Home-page: https://github.com/CERNDocumentServer/record-recommender
Author: CERN
Author-email: cds.support@cern.ch
License: GPLv2
Keywords: invenio recommendation
Platform: any
Classifier: Environment :: Web Environment
Classifier: Intended Audience :: Developers
Classifier: License :: OSI Approved :: GNU General Public License v2 (GPLv2)
Classifier: Operating System :: OS Independent
Classifier: Programming Language :: Python
Classifier: Topic :: Internet :: WWW/HTTP :: Dynamic Content
Classifier: Topic :: Software Development :: Libraries :: Python Modules
Classifier: Programming Language :: Python :: 2
Classifier: Programming Language :: Python :: 2.7
Classifier: Programming Language :: Python :: 3
Classifier: Programming Language :: Python :: 3.3
Classifier: Programming Language :: Python :: 3.4
Classifier: Programming Language :: Python :: 3.5
Classifier: Development Status :: 2 - Pre-Alpha
